tamilocrx/__init__.py
tamilocrx/ocr.py
tamilocrx/configs/__init__.py
tamilocrx/configs/bench.yaml
tamilocrx/configs/main.yaml
tamilocrx/configs/tune.yaml
tamilocrx/configs/charset/36_lowercase.yaml
tamilocrx/configs/charset/62_mixed-case.yaml
tamilocrx/configs/charset/94_full.yaml
tamilocrx/configs/charset/__init__.py
tamilocrx/configs/experiment/__init__.py
tamilocrx/configs/experiment/parseq-patch16-224.yaml
tamilocrx/configs/experiment/parseq-tiny.yaml
tamilocrx/configs/experiment/parseq.yaml
tamilocrx/configs/model/__init__.py
tamilocrx/configs/model/abinet.yaml
tamilocrx/configs/model/crnn.yaml
tamilocrx/configs/model/parseq.yaml
tamilocrx/configs/model/trba.yaml
tamilocrx/configs/model/vitstr.yaml
tamilocrx/craft_text_detector/__init__.py
tamilocrx/craft_text_detector/craft_utils.py
tamilocrx/craft_text_detector/file_utils.py
tamilocrx/craft_text_detector/image_utils.py
tamilocrx/craft_text_detector/predict.py
tamilocrx/craft_text_detector/setup.py
tamilocrx/craft_text_detector/test.py
tamilocrx/craft_text_detector/torch_utils.py
tamilocrx/craft_text_detector/models/__init__.py
tamilocrx/craft_text_detector/models/craftnet.py
tamilocrx/craft_text_detector/models/refinenet.py
tamilocrx/craft_text_detector/models/basenet/__init__.py
tamilocrx/craft_text_detector/models/basenet/vgg16_bn.py
tamilocrx/strhub/__init__.py
tamilocrx/strhub/data/__init__.py
tamilocrx/strhub/data/utils.py
tamilocrx/strhub/models/__init__.py
tamilocrx/strhub/models/base.py
tamilocrx/strhub/models/utils.py
tamilocrx/strhub/models/__pycache__/__init__.cpython-312.pyc
tamilocrx/strhub/models/__pycache__/base.cpython-312.pyc
tamilocrx/strhub/models/__pycache__/utils.cpython-312.pyc
tamilocrx/strhub/models/parseq/__init__.py
tamilocrx/strhub/models/parseq/modules.py
tamilocrx/strhub/models/parseq/system.py
tamilocrx/strhub/models/parseq/__pycache__/__init__.cpython-312.pyc
tamilocrx/strhub/models/parseq/__pycache__/modules.cpython-312.pyc
tamilocrx-0.1.0.dist-info/licenses/LICENSE
tamilocrx-0.1.0.dist-info/METADATA
tamilocrx-0.1.0.dist-info/WHEEL
tamilocrx-0.1.0.dist-info/entry_points.txt
tamilocrx-0.1.0.dist-info/top_level.txt
tamilocrx-0.1.0.dist-info/RECORD
