Metadata-Version: 2.4
Name: tamilocrx
Version: 0.1.0
Summary: Tamil OCR engine using PARSeq and CRAFT
Home-page: https://github.com/cyber-bytezz/tamilocrx
Author: Aro Barath Chandru B
Author-email: Aro Barath Chandru B <chandru2021007@gmail.com>
License: MIT License
Project-URL: Homepage, https://github.com/cyber-bytezz/tamilocrx
Keywords: ocr,tamilocr,tamil ocr,ocr engine,indian ocr,craft,parseq
Classifier: License :: OSI Approved :: MIT License
Classifier: Programming Language :: Python
Classifier: Programming Language :: Python :: 3
Requires-Python: >=3.8
License-File: LICENSE
Requires-Dist: torch>=2
Requires-Dist: torchvision>=0.15.1
Requires-Dist: Pillow>=10.0.0
Requires-Dist: opencv-python
Requires-Dist: numpy
Requires-Dist: gdown
Requires-Dist: pytorch-lightning==1.9.5
Requires-Dist: matplotlib
Requires-Dist: scikit-image
Requires-Dist: timm
Requires-Dist: gradio
Requires-Dist: pyyaml
Requires-Dist: requests
Provides-Extra: dev
Requires-Dist: black; extra == "dev"
Requires-Dist: bumpver; extra == "dev"
Requires-Dist: isort; extra == "dev"
Requires-Dist: pip-tools; extra == "dev"
Requires-Dist: pytest; extra == "dev"
Dynamic: author
Dynamic: home-page
Dynamic: license-file
Dynamic: requires-python
